cell_load/__init__.py
cell_load/config.py
cell_load/py.typed
cell_load/_cli/__init__.py
cell_load/_cli/filter_on_target_knockdown.py
cell_load/data_modules/__init__.py
cell_load/data_modules/perturbation_dataloader.py
cell_load/data_modules/samplers.py
cell_load/data_modules/tasks.py
cell_load/dataset/__init__.py
cell_load/dataset/_metadata.py
cell_load/dataset/_perturbation.py
cell_load/mapping_strategies/__init__.py
cell_load/mapping_strategies/batch.py
cell_load/mapping_strategies/mapping_strategies.py
cell_load/mapping_strategies/random.py
cell_load/utils/data_utils.py
cell_load/utils/modules.py
cell_load/utils/singleton.py
cell_load-0.8.7.dist-info/METADATA
cell_load-0.8.7.dist-info/WHEEL
cell_load-0.8.7.dist-info/entry_points.txt
cell_load-0.8.7.dist-info/licenses/LICENSE
cell_load-0.8.7.dist-info/RECORD
