Metadata-Version: 2.4
Name: cell-load
Version: 0.8.7
Summary: Dataloaders for training models on huge single-cell datasets
Author-email: Abhinav Adduri <abhinav.adduri@arcinstitute.org>, Yusuf Roohani <yusuf.roohani@arcinstitute.org>, Noam Teyssier <noam.teyssier@arcinstitute.org>, Rishi Verma <rishi.verma@arcinstitute.org>, Francis Chalissery <francis.chalissery@arcinstitute.org>, Beatrice Bevilacqua <beatrice.bevilacqua@arcinstitute.org>
License-File: LICENSE
Requires-Python: <3.13,>=3.10
Requires-Dist: anndata>=0.9.1
Requires-Dist: lightning>=2.0.0
Requires-Dist: scanpy>=1.9.0
Requires-Dist: toml>=0.10.2
Requires-Dist: torch>=1.13.0
